example_pkg/__init__.py
aganhui-0.0.2.dist-info/LICENSE
aganhui-0.0.2.dist-info/METADATA
aganhui-0.0.2.dist-info/WHEEL
aganhui-0.0.2.dist-info/top_level.txt
aganhui-0.0.2.dist-info/RECORD
