Metadata-Version: 2.1
Name: aganhui
Version: 0.0.2
Summary: ygh's package
Home-page: https://github.com/pypa/sampleproject
Author: aganhui
Author-email: 907402005@qq.com
License: UNKNOWN
Platform: UNKNOWN
Classifier: Programming Language :: Python :: 3
Classifier: License :: OSI Approved :: MIT License
Classifier: Operating System :: OS Independent
